merobox/__init__.py
merobox/cli.py
merobox/testing.py
merobox/commands/__init__.py
merobox/commands/binary_manager.py
merobox/commands/blob.py
merobox/commands/call.py
merobox/commands/client.py
merobox/commands/constants.py
merobox/commands/health.py
merobox/commands/identity.py
merobox/commands/install.py
merobox/commands/join.py
merobox/commands/list.py
merobox/commands/logs.py
merobox/commands/manager.py
merobox/commands/nuke.py
merobox/commands/proposals.py
merobox/commands/result.py
merobox/commands/retry.py
merobox/commands/run.py
merobox/commands/stop.py
merobox/commands/utils.py
merobox/commands/bootstrap/__init__.py
merobox/commands/bootstrap/bootstrap.py
merobox/commands/bootstrap/config.py
merobox/commands/bootstrap/run/__init__.py
merobox/commands/bootstrap/run/executor.py
merobox/commands/bootstrap/run/run.py
merobox/commands/bootstrap/steps/__init__.py
merobox/commands/bootstrap/steps/assertion.py
merobox/commands/bootstrap/steps/base.py
merobox/commands/bootstrap/steps/blob.py
merobox/commands/bootstrap/steps/context.py
merobox/commands/bootstrap/steps/execute.py
merobox/commands/bootstrap/steps/identity.py
merobox/commands/bootstrap/steps/install.py
merobox/commands/bootstrap/steps/invite_open.py
merobox/commands/bootstrap/steps/join.py
merobox/commands/bootstrap/steps/join_open.py
merobox/commands/bootstrap/steps/json_assertion.py
merobox/commands/bootstrap/steps/proposals.py
merobox/commands/bootstrap/steps/repeat.py
merobox/commands/bootstrap/steps/script.py
merobox/commands/bootstrap/steps/wait.py
merobox/commands/bootstrap/validate/__init__.py
merobox/commands/bootstrap/validate/validator.py
merobox-0.2.3.dist-info/licenses/LICENSE
merobox-0.2.3.dist-info/METADATA
merobox-0.2.3.dist-info/WHEEL
merobox-0.2.3.dist-info/entry_points.txt
merobox-0.2.3.dist-info/top_level.txt
merobox-0.2.3.dist-info/RECORD
