Metadata-Version: 2.4
Name: merobox
Version: 0.2.3
Summary: A Python CLI tool for managing Calimero nodes in Docker containers
Home-page: https://github.com/merobox/merobox
Author: Merobox Team
Author-email: "Calimero Ltd." <engineering@calimero.network>
License: MIT
Classifier: Development Status :: 4 - Beta
Classifier: Intended Audience :: Developers
Classifier: License :: OSI Approved :: MIT License
Classifier: Programming Language :: Python :: 3
Classifier: Programming Language :: Python :: 3.9
Classifier: Programming Language :: Python :: 3.10
Classifier: Programming Language :: Python :: 3.11
Requires-Python: >=3.9
License-File: LICENSE
Requires-Dist: click>=8.0.0
Requires-Dist: docker>=6.0.0
Requires-Dist: rich>=13.0.0
Requires-Dist: PyYAML>=6.0.0
Requires-Dist: calimero-client-py==0.2.7
Requires-Dist: aiohttp>=3.9.0
Provides-Extra: dev
Requires-Dist: black>=25.0.0; extra == "dev"
Requires-Dist: ruff>=0.1.0; extra == "dev"
Requires-Dist: pytest>=8.0.0; extra == "dev"
Requires-Dist: pytest-asyncio>=0.21.0; extra == "dev"
Requires-Dist: pytest-mock>=3.10.0; extra == "dev"
Requires-Dist: pre-commit>=3.0.0; extra == "dev"
Requires-Dist: pyinstaller>=6.0.0; extra == "dev"
Dynamic: author
Dynamic: home-page
Dynamic: license-file
Dynamic: requires-python
